tankerkoenig/__init__.py
tankerkoenig/client.py
tankerkoenig/exceptions.py
tankerkoenig/models.py
tankerkoenig-0.0.4.dist-info/LICENSE
tankerkoenig-0.0.4.dist-info/METADATA
tankerkoenig-0.0.4.dist-info/WHEEL
tankerkoenig-0.0.4.dist-info/top_level.txt
tankerkoenig-0.0.4.dist-info/RECORD
