Metadata-Version: 2.1
Name: tankerkoenig
Version: 0.0.4
Summary: Wrapper for creativecommons.tankerkoenig.de API
Home-page: https://github.com/hugohabicht01/tankerkoenig-python
Author: hugohabicht01
Author-email: jodeldiplominhaber@pm.me
License: UNKNOWN
Project-URL: Bug Reports, https://github.com/hugohabicht01/tankerkoenig-python/issues
Project-URL: Source, https://github.com/hugohabicht01/tankerkoenig-python
Platform: UNKNOWN
Classifier: Development Status :: 3 - Alpha
Classifier: Intended Audience :: Developers
Classifier: Topic :: Internet
Classifier: License :: OSI Approved :: MIT License
Classifier: Programming Language :: Python :: 3
Classifier: Programming Language :: Python :: 3.8
Requires-Python: >=3.8, <4
License-File: LICENSE
Requires-Dist: certifi (==2021.5.30)
Requires-Dist: pydantic (==1.8.2)
Requires-Dist: requests (==2.26.0)
Requires-Dist: responses (==0.13.3)
Requires-Dist: typing-extensions (==3.10.0.0)
Requires-Dist: six (==1.16.0) ; python_version >= "2.7" and python_version not in "3.0, 3.1, 3.2, 3.3"
Requires-Dist: urllib3 (==1.26.6) ; python_version >= "2.7" and python_version not in "3.0, 3.1, 3.2, 3.3, 3.4" and python_version < "4"
Requires-Dist: charset-normalizer (==2.0.3) ; python_version >= "3"
Requires-Dist: idna (==3.2) ; python_version >= "3"
Provides-Extra: dev
